README.rst
depth_gauge.py
mucor.py
mucor_config.py
setup.py
mucor.egg-info/PKG-INFO
mucor.egg-info/SOURCES.txt
mucor.egg-info/dependency_links.txt
mucor.egg-info/requires.txt
mucor.egg-info/top_level.txt