Metadata-Version: 1.1
Name: mucor
Version: 1.51
Summary: Genomic Variant Aggregation and Mutation Correlation
Home-page: http://github.com/blachlylab/mucor
Author: James Blachly
Author-email: james blachly at gmail com
License: GNU GPLv3
Keywords: sequencing,VCF,mutation,variant
Platform: UNKNOWN
Classifier: Development Status :: 5 - Production/Stable
Classifier: Environment :: Console
Classifier: Intended Audience :: Healthcare Industry
Classifier: Intended Audience :: Science/Research
Classifier: License :: OSI Approved :: GNU General Public License v3 (GPLv3)
Classifier: Natural Language :: English
Classifier: Operating System :: OS Independent
Classifier: Programming Language :: Python
Classifier: Topic :: Scientific/Engineering :: Bio-Informatics
